metronome_pulse_core/__init__.py
metronome_pulse_core/base.py
metronome_pulse_core/interfaces.py
metronome_pulse_core-0.1.0.dist-info/METADATA
metronome_pulse_core-0.1.0.dist-info/WHEEL
metronome_pulse_core-0.1.0.dist-info/RECORD
