Metadata-Version: 2.4
Name: metronome-pulse-core
Version: 0.1.0
Summary: Core interfaces and abstractions for DataPulse connectors - a high-performance, async-first data connectivity framework
Project-URL: Homepage, https://github.com/TheDataMaestros/metronome-pulse-core
Project-URL: Repository, https://github.com/TheDataMaestros/metronome-pulse-core
Project-URL: Documentation, https://thedatamaestros.dev/docs/pulse-core
Project-URL: Issues, https://github.com/TheDataMaestros/metronome-pulse-core/issues
Project-URL: Changelog, https://github.com/TheDataMaestros/metronome-pulse-core/blob/main/CHANGELOG.md
Project-URL: Download, https://pypi.org/project/metronome-pulse-core/#files
Author-email: TheDataMaestros <team@thedatamaestros.dev>
Maintainer-email: TheDataMaestros <team@thedatamaestros.dev>
License: MIT
Keywords: async,connector,data-pipeline,data-quality,database,etl
Classifier: Development Status :: 4 - Beta
Classifier: Framework :: AsyncIO
Classifier: Intended Audience :: Developers
Classifier: Intended Audience :: System Administrators
Classifier: License :: OSI Approved :: MIT License
Classifier: Operating System :: OS Independent
Classifier: Programming Language :: Python :: 3
Classifier: Programming Language :: Python :: 3.9
Classifier: Programming Language :: Python :: 3.10
Classifier: Programming Language :: Python :: 3.11
Classifier: Programming Language :: Python :: 3.12
Classifier: Programming Language :: Python :: 3.13
Classifier: Topic :: Database
Classifier: Topic :: Software Development :: Libraries :: Python Modules
Classifier: Topic :: System :: Networking
Classifier: Typing :: Typed
Requires-Python: >=3.9
Requires-Dist: pydantic>=2.0.0
Requires-Dist: typing-extensions>=4.0.0; python_version < '3.12'
Provides-Extra: dev
Requires-Dist: black>=23.0.0; extra == 'dev'
Requires-Dist: isort>=5.12.0; extra == 'dev'
Requires-Dist: mypy>=1.0.0; extra == 'dev'
Requires-Dist: pre-commit>=3.0.0; extra == 'dev'
Requires-Dist: pytest-asyncio>=0.21.0; extra == 'dev'
Requires-Dist: pytest-cov>=4.0.0; extra == 'dev'
Requires-Dist: pytest>=7.0.0; extra == 'dev'
Requires-Dist: ruff>=0.1.0; extra == 'dev'
Provides-Extra: docs
Requires-Dist: myst-parser>=2.0.0; extra == 'docs'
Requires-Dist: sphinx-rtd-theme>=1.3.0; extra == 'docs'
Requires-Dist: sphinx>=7.0.0; extra == 'docs'
Provides-Extra: test
Requires-Dist: pytest-asyncio>=0.21.0; extra == 'test'
Requires-Dist: pytest-benchmark>=4.0.0; extra == 'test'
Requires-Dist: pytest-cov>=4.0.0; extra == 'test'
Requires-Dist: pytest-mock>=3.10.0; extra == 'test'
Requires-Dist: pytest>=7.0.0; extra == 'test'
